allocation_language/__init__.py
allocation_language/custom_exceptions.py
allocation_language/lexer.py
allocation_language/make_contract.py
allocation_language/parser.py
allocation_language/alloc_lang_data_containers/__init__.py
allocation_language/alloc_lang_data_containers/converters.py
allocation_language/alloc_lang_data_containers/event_dataclasses.py
allocation_language/ast_nodes/__init__.py
allocation_language/ast_nodes/alloc_lang_aggregate.py
allocation_language/ast_nodes/alloc_lang_alloc.py
allocation_language/ast_nodes/alloc_lang_assess.py
allocation_language/ast_nodes/alloc_lang_binops.py
allocation_language/ast_nodes/alloc_lang_blocks.py
allocation_language/ast_nodes/alloc_lang_discard.py
allocation_language/ast_nodes/alloc_lang_primitives.py
allocation_language/ast_nodes/alloc_lang_scope.py
allocation_language/ast_nodes/alloc_lang_set.py
allocation_language-0.0.4.dist-info/LICENSE
allocation_language-0.0.4.dist-info/METADATA
allocation_language-0.0.4.dist-info/WHEEL
allocation_language-0.0.4.dist-info/top_level.txt
allocation_language-0.0.4.dist-info/RECORD
