Metadata-Version: 2.1
Name: allocation-language
Version: 0.0.4
Summary: Language intented to construct the financial behaviour of (re)insurance contracts.
Home-page: UNKNOWN
Author: Mammen Joseph
Author-email: tmammenjoseph@gmail.com
Maintainer: Mammen Joseph
Maintainer-email: tmammenjoseph@gmail.com
License: UNKNOWN
Platform: UNKNOWN
Requires-Python: >=3.6
License-File: LICENSE
Requires-Dist: rply
